rst_tools/__init__.py
rst_tools/models/__init__.py
rst_tools/models/maximum_dependency_attributes.py
rst_tools/models/reduct.py
rst_tools/models/roughsets.py
rst_tools/models/similarity.py
rst_tools/models/vprs.py
rst_tools-0.1.8.dist-info/WHEEL
rst_tools-0.1.8.dist-info/METADATA
rst_tools-0.1.8.dist-info/RECORD
