Metadata-Version: 2.1
Name: rst-tools
Version: 0.1.8
Summary: Rough sets implementation in Python
Home-page: https://github.com/rhsitorus/rst-tools
Author: Rofilde Hasudungan
Author-email: rofilde@gmail.com
Requires-Python: >=3.7,<4.0
Classifier: Programming Language :: Python :: 3
Classifier: Programming Language :: Python :: 3.10
Classifier: Programming Language :: Python :: 3.7
Classifier: Programming Language :: Python :: 3.8
Classifier: Programming Language :: Python :: 3.9
Requires-Dist: pandas
Project-URL: Repository, https://github.com/rhsitorus/rst-tools
